{ 
    "_id" : ObjectId("5863a22aa7770f2681a7a507"), 
    "RecordID" : NumberInt(1), 
    "stationid" : ObjectId("584922ef577e7e6f43b7734f"), 
    "starttime" : ISODate("2016-12-28T11:31:43.062+0000"), 
    "cyclenums" : NumberInt(0), 
    "updateStatus" : NumberInt(1), 
    "stationtype" : "Minor", 
    "offpeekduration" : 2.5171333333333332, 
    "peekduration" : 2.5171333333333332, 
    "timeduration" : 5.0342666666666664, 
    "status" : NumberInt(2), 
    "__v" : NumberInt(0), 
    "endtime" : ISODate("2016-12-28T11:36:45.118+0000"), 
    "updatedcyclenums" : NumberInt(1)
}
{ 
    "_id" : ObjectId("5863aa07a7770f2681a7aa87"), 
    "RecordID" : NumberInt(2), 
    "stationid" : ObjectId("584922ef577e7e6f43b7734f"), 
    "starttime" : ISODate("2016-12-28T12:05:15.380+0000"), 
    "cyclenums" : NumberInt(0), 
    "updateStatus" : NumberInt(1), 
    "stationtype" : "Minor", 
    "offpeekduration" : 0.327875, 
    "peekduration" : 0.327875, 
    "timeduration" : 0.65575, 
    "status" : NumberInt(2), 
    "__v" : NumberInt(0), 
    "endtime" : ISODate("2016-12-28T12:05:54.725+0000"), 
    "updatedcyclenums" : NumberInt(1)
}
{ 
    "_id" : ObjectId("5863ab16a7770f2681a7ac7d"), 
    "RecordID" : NumberInt(3), 
    "stationid" : ObjectId("584922ef577e7e6f43b7734f"), 
    "starttime" : ISODate("2016-12-28T12:09:46.497+0000"), 
    "cyclenums" : NumberInt(0), 
    "updateStatus" : NumberInt(1), 
    "stationtype" : "Minor", 
    "offpeekduration" : 0.5190083333333333, 
    "peekduration" : 0.5190083333333333, 
    "timeduration" : 1.0380166666666666, 
    "status" : NumberInt(2), 
    "__v" : NumberInt(0), 
    "endtime" : ISODate("2016-12-28T12:10:48.778+0000"), 
    "updatedcyclenums" : NumberInt(1)
}
{ 
    "_id" : ObjectId("5863ab2ba7770f2681a7ad1c"), 
    "RecordID" : NumberInt(4), 
    "stationid" : ObjectId("584922ef577e7e6f43b7734f"), 
    "starttime" : ISODate("2016-12-28T12:10:08.623+0000"), 
    "cyclenums" : NumberInt(0), 
    "updateStatus" : NumberInt(1), 
    "stationtype" : "Minor", 
    "offpeekduration" : 0.41875833333333334, 
    "peekduration" : 0.41875833333333334, 
    "timeduration" : 0.8375166666666667, 
    "status" : NumberInt(2), 
    "__v" : NumberInt(0), 
    "endtime" : ISODate("2016-12-28T12:10:58.874+0000"), 
    "updatedcyclenums" : NumberInt(1)
}
{ 
    "_id" : ObjectId("5863ab52a7770f2681a7adc7"), 
    "RecordID" : NumberInt(5), 
    "stationid" : ObjectId("584922ef577e7e6f43b7734f"), 
    "starttime" : ISODate("2016-12-28T12:10:46.506+0000"), 
    "cyclenums" : NumberInt(0), 
    "updateStatus" : NumberInt(1), 
    "stationtype" : "Minor", 
    "offpeekduration" : 0.5023, 
    "peekduration" : 0.5023, 
    "timeduration" : 1.0046, 
    "status" : NumberInt(2), 
    "__v" : NumberInt(0), 
    "endtime" : ISODate("2016-12-28T12:11:46.782+0000"), 
    "updatedcyclenums" : NumberInt(1)
}
{ 
    "_id" : ObjectId("5863ab52a7770f2681a7adc8"), 
    "RecordID" : NumberInt(6), 
    "stationid" : ObjectId("584922ef577e7e6f43b7734f"), 
    "starttime" : ISODate("2016-12-28T12:10:46.436+0000"), 
    "cyclenums" : NumberInt(0), 
    "updateStatus" : NumberInt(1), 
    "stationtype" : "Minor", 
    "offpeekduration" : 0.6025833333333334, 
    "peekduration" : 0.6025833333333334, 
    "timeduration" : 1.2051666666666667, 
    "status" : NumberInt(2), 
    "__v" : NumberInt(0), 
    "endtime" : ISODate("2016-12-28T12:11:58.746+0000"), 
    "updatedcyclenums" : NumberInt(1)
}
{ 
    "_id" : ObjectId("5863ab5fa7770f2681a7adfa"), 
    "RecordID" : NumberInt(7), 
    "stationid" : ObjectId("584922ef577e7e6f43b7734f"), 
    "starttime" : ISODate("2016-12-28T12:10:59.278+0000"), 
    "cyclenums" : NumberInt(0), 
    "updateStatus" : NumberInt(1), 
    "stationtype" : "Minor", 
    "offpeekduration" : 9.299958333333333, 
    "peekduration" : 9.299958333333333, 
    "timeduration" : 18.599916666666665, 
    "status" : NumberInt(2), 
    "__v" : NumberInt(0), 
    "endtime" : ISODate("2016-12-28T12:29:35.273+0000"), 
    "updatedcyclenums" : NumberInt(1)
}
{ 
    "_id" : ObjectId("5863ab8aa7770f2681a7ae83"), 
    "RecordID" : NumberInt(8), 
    "stationid" : ObjectId("584922ef577e7e6f43b7734f"), 
    "starttime" : ISODate("2016-12-28T12:11:42.064+0000"), 
    "cyclenums" : NumberInt(0), 
    "updateStatus" : NumberInt(1), 
    "stationtype" : "Minor", 
    "offpeekduration" : 471.6664416666667, 
    "peekduration" : 471.6664416666667, 
    "timeduration" : 943.3328833333334, 
    "status" : NumberInt(2), 
    "__v" : NumberInt(0), 
    "endtime" : ISODate("2016-12-29T03:55:02.037+0000"), 
    "updatedcyclenums" : NumberInt(1)
}
{ 
    "_id" : ObjectId("5863ab8aa7770f2681a7ae84"), 
    "RecordID" : NumberInt(9), 
    "stationid" : ObjectId("584922ef577e7e6f43b7734f"), 
    "starttime" : ISODate("2016-12-28T12:11:42.064+0000"), 
    "cyclenums" : NumberInt(0), 
    "updateStatus" : NumberInt(1), 
    "stationtype" : "Minor", 
    "offpeekduration" : 481.5314583333333, 
    "peekduration" : 481.5314583333333, 
    "timeduration" : 963.0629166666666, 
    "status" : NumberInt(2), 
    "__v" : NumberInt(0), 
    "endtime" : ISODate("2016-12-29T04:14:45.839+0000"), 
    "updatedcyclenums" : NumberInt(1)
}
{ 
    "_id" : ObjectId("5863ab99a7770f2681a7aea8"), 
    "RecordID" : NumberInt(10), 
    "stationid" : ObjectId("584922ef577e7e6f43b7734f"), 
    "starttime" : ISODate("2016-12-28T12:11:58.100+0000"), 
    "cyclenums" : NumberInt(0), 
    "updateStatus" : NumberInt(1), 
    "stationtype" : "Minor", 
    "offpeekduration" : 631.9926083333334, 
    "peekduration" : 631.9926083333334, 
    "timeduration" : 1263.9852166666667, 
    "status" : NumberInt(2), 
    "__v" : NumberInt(0), 
    "endtime" : ISODate("2016-12-29T09:15:57.213+0000"), 
    "updatedcyclenums" : NumberInt(1)
}
{ 
    "_id" : ObjectId("5863ad3ca7770f2681a7afd2"), 
    "RecordID" : NumberInt(11), 
    "stationid" : ObjectId("5849235cc31f7c020a0f6cb8"), 
    "starttime" : ISODate("2016-12-28T12:19:22.505+0000"), 
    "cyclenums" : NumberInt(0), 
    "updateStatus" : NumberInt(1), 
    "stationtype" : "Minor", 
    "offpeekduration" : 0.1284, 
    "peekduration" : 0.1284, 
    "timeduration" : 0.2568, 
    "status" : NumberInt(2), 
    "__v" : NumberInt(0), 
    "endtime" : ISODate("2016-12-28T12:19:37.913+0000"), 
    "updatedcyclenums" : NumberInt(1)
}
{ 
    "_id" : ObjectId("5863ad56a7770f2681a7affe"), 
    "RecordID" : NumberInt(12), 
    "stationid" : ObjectId("5849235cc31f7c020a0f6cb8"), 
    "starttime" : ISODate("2016-12-28T12:19:46.948+0000"), 
    "cyclenums" : NumberInt(0), 
    "updateStatus" : NumberInt(1), 
    "stationtype" : "Minor", 
    "offpeekduration" : 0.018525, 
    "peekduration" : 0.018525, 
    "timeduration" : 0.03705, 
    "status" : NumberInt(2), 
    "__v" : NumberInt(0), 
    "endtime" : ISODate("2016-12-28T12:19:49.171+0000"), 
    "updatedcyclenums" : NumberInt(1)
}
{ 
    "_id" : ObjectId("5863ad5ba7770f2681a7b021"), 
    "RecordID" : NumberInt(13), 
    "stationid" : ObjectId("5849235cc31f7c020a0f6cb8"), 
    "starttime" : ISODate("2016-12-28T12:19:54.519+0000"), 
    "cyclenums" : NumberInt(0), 
    "updateStatus" : NumberInt(1), 
    "stationtype" : "Minor", 
    "offpeekduration" : 0.35185833333333333, 
    "peekduration" : 0.35185833333333333, 
    "timeduration" : 0.7037166666666667, 
    "status" : NumberInt(2), 
    "__v" : NumberInt(0), 
    "endtime" : ISODate("2016-12-28T12:20:36.742+0000"), 
    "updatedcyclenums" : NumberInt(1)
}
{ 
    "_id" : ObjectId("5863adbea7770f2681a7b1cc"), 
    "RecordID" : NumberInt(14), 
    "stationid" : ObjectId("5849235cc31f7c020a0f6cb8"), 
    "starttime" : ISODate("2016-12-28T12:21:31.088+0000"), 
    "cyclenums" : NumberInt(0), 
    "updateStatus" : NumberInt(1), 
    "stationtype" : "Minor", 
    "offpeekduration" : 0.06170833333333333, 
    "peekduration" : 0.06170833333333333, 
    "timeduration" : 0.12341666666666666, 
    "status" : NumberInt(2), 
    "__v" : NumberInt(0), 
    "endtime" : ISODate("2016-12-28T12:21:38.493+0000"), 
    "updatedcyclenums" : NumberInt(1)
}
{ 
    "_id" : ObjectId("5863ae4fa7770f2681a7b2d8"), 
    "RecordID" : NumberInt(15), 
    "stationid" : ObjectId("5849235cc31f7c020a0f6cb8"), 
    "starttime" : ISODate("2016-12-28T12:23:56.280+0000"), 
    "cyclenums" : NumberInt(0), 
    "updateStatus" : NumberInt(1), 
    "stationtype" : "Minor", 
    "offpeekduration" : 0.10210833333333333, 
    "peekduration" : 0.10210833333333333, 
    "timeduration" : 0.20421666666666666, 
    "status" : NumberInt(2), 
    "__v" : NumberInt(0), 
    "endtime" : ISODate("2016-12-28T12:24:08.533+0000"), 
    "updatedcyclenums" : NumberInt(1)
}
{ 
    "_id" : ObjectId("5863ae61a7770f2681a7b307"), 
    "RecordID" : NumberInt(16), 
    "stationid" : ObjectId("5849235cc31f7c020a0f6cb8"), 
    "starttime" : ISODate("2016-12-28T12:24:13.849+0000"), 
    "cyclenums" : NumberInt(0), 
    "updateStatus" : NumberInt(1), 
    "stationtype" : "Minor", 
    "offpeekduration" : 0.238975, 
    "peekduration" : 0.238975, 
    "timeduration" : 0.47795, 
    "status" : NumberInt(2), 
    "__v" : NumberInt(0), 
    "endtime" : ISODate("2016-12-28T12:24:42.526+0000"), 
    "updatedcyclenums" : NumberInt(1)
}
{ 
    "_id" : ObjectId("5863ae91a7770f2681a7b399"), 
    "RecordID" : NumberInt(17), 
    "stationid" : ObjectId("5849235cc31f7c020a0f6cb8"), 
    "starttime" : ISODate("2016-12-28T12:25:02.518+0000"), 
    "cyclenums" : NumberInt(0), 
    "updateStatus" : NumberInt(1), 
    "stationtype" : "Minor", 
    "offpeekduration" : 4.051416666666666, 
    "peekduration" : 4.051416666666666, 
    "timeduration" : 8.102833333333333, 
    "status" : NumberInt(2), 
    "__v" : NumberInt(0), 
    "endtime" : ISODate("2016-12-28T12:33:08.688+0000"), 
    "updatedcyclenums" : NumberInt(1)
}
{ 
    "_id" : ObjectId("5863afbaa7770f2681a7b49f"), 
    "RecordID" : NumberInt(18), 
    "stationid" : ObjectId("584922ef577e7e6f43b7734f"), 
    "starttime" : ISODate("2016-12-28T12:29:34.878+0000"), 
    "cyclenums" : NumberInt(0), 
    "updateStatus" : NumberInt(1), 
    "stationtype" : "Minor", 
    "offpeekduration" : 627.860275, 
    "peekduration" : 627.860275, 
    "timeduration" : 1255.72055, 
    "status" : NumberInt(2), 
    "__v" : NumberInt(0), 
    "endtime" : ISODate("2016-12-29T09:25:18.111+0000"), 
    "updatedcyclenums" : NumberInt(1)
}
{ 
    "_id" : ObjectId("5863b0c0a7770f2681a7b5de"), 
    "RecordID" : NumberInt(19), 
    "stationid" : ObjectId("5849235cc31f7c020a0f6cb8"), 
    "starttime" : ISODate("2016-12-28T12:34:21.804+0000"), 
    "cyclenums" : NumberInt(0), 
    "updateStatus" : NumberInt(0), 
    "stationtype" : "Minor", 
    "offpeekduration" : NumberInt(0), 
    "peekduration" : NumberInt(0), 
    "timeduration" : NumberInt(0), 
    "status" : NumberInt(2), 
    "__v" : NumberInt(0)
}
{ 
    "_id" : ObjectId("5863b0c0a7770f2681a7b5df"), 
    "RecordID" : NumberInt(20), 
    "stationid" : ObjectId("5849235cc31f7c020a0f6cb8"), 
    "starttime" : ISODate("2016-12-28T12:34:22.007+0000"), 
    "cyclenums" : NumberInt(0), 
    "updateStatus" : NumberInt(0), 
    "stationtype" : "Minor", 
    "offpeekduration" : NumberInt(0), 
    "peekduration" : NumberInt(0), 
    "timeduration" : NumberInt(0), 
    "status" : NumberInt(2), 
    "__v" : NumberInt(0)
}
{ 
    "_id" : ObjectId("5863b108a7770f2681a7b5ef"), 
    "RecordID" : NumberInt(21), 
    "stationid" : ObjectId("584922ef577e7e6f43b7734f"), 
    "starttime" : ISODate("2016-12-28T12:35:09.022+0000"), 
    "cyclenums" : NumberInt(0), 
    "updateStatus" : NumberInt(1), 
    "stationtype" : "Minor", 
    "offpeekduration" : 625.308925, 
    "peekduration" : 625.308925, 
    "timeduration" : 1250.61785, 
    "status" : NumberInt(2), 
    "__v" : NumberInt(0), 
    "endtime" : ISODate("2016-12-29T09:25:46.093+0000"), 
    "updatedcyclenums" : NumberInt(1)
}
{ 
    "_id" : ObjectId("5864782ba7770f2681a7b62b"), 
    "RecordID" : NumberInt(22), 
    "stationid" : ObjectId("58491323d51ad2238a1af65b"), 
    "starttime" : ISODate("2016-12-29T02:44:51.378+0000"), 
    "cyclenums" : NumberInt(0), 
    "updateStatus" : NumberInt(1), 
    "stationtype" : "Minor", 
    "offpeekduration" : 57.15058333333333, 
    "peekduration" : 57.15058333333333, 
    "timeduration" : 114.30116666666666, 
    "status" : NumberInt(2), 
    "__v" : NumberInt(0), 
    "endtime" : ISODate("2016-12-29T04:39:09.448+0000"), 
    "updatedcyclenums" : NumberInt(1)
}
{ 
    "_id" : ObjectId("58648d4ca7770f2681a7b6af"), 
    "RecordID" : NumberInt(23), 
    "stationid" : ObjectId("584922ef577e7e6f43b7734f"), 
    "starttime" : ISODate("2016-12-29T04:15:02.086+0000"), 
    "cyclenums" : NumberInt(0), 
    "updateStatus" : NumberInt(1), 
    "stationtype" : "Minor", 
    "offpeekduration" : 155.53334166666667, 
    "peekduration" : 155.53334166666667, 
    "timeduration" : 311.06668333333334, 
    "status" : NumberInt(2), 
    "__v" : NumberInt(0), 
    "endtime" : ISODate("2016-12-29T09:26:06.087+0000"), 
    "updatedcyclenums" : NumberInt(1)
}
{ 
    "_id" : ObjectId("58648d4ca7770f2681a7b6b2"), 
    "RecordID" : NumberInt(24), 
    "stationid" : ObjectId("584922ef577e7e6f43b7734f"), 
    "starttime" : ISODate("2016-12-29T04:15:02.086+0000"), 
    "cyclenums" : NumberInt(0), 
    "updateStatus" : NumberInt(1), 
    "stationtype" : "Minor", 
    "offpeekduration" : 155.73326666666668, 
    "peekduration" : 155.73326666666668, 
    "timeduration" : 311.46653333333336, 
    "status" : NumberInt(2), 
    "__v" : NumberInt(0), 
    "endtime" : ISODate("2016-12-29T09:26:30.078+0000"), 
    "updatedcyclenums" : NumberInt(1)
}
{ 
    "_id" : ObjectId("58649182a7770f2681a7ba8e"), 
    "RecordID" : NumberInt(25), 
    "stationid" : ObjectId("584922ef577e7e6f43b7734f"), 
    "starttime" : ISODate("2016-12-29T04:33:01.636+0000"), 
    "cyclenums" : NumberInt(0), 
    "updateStatus" : NumberInt(1), 
    "stationtype" : "Minor", 
    "offpeekduration" : 146.93936666666667, 
    "peekduration" : 146.93936666666667, 
    "timeduration" : 293.87873333333334, 
    "status" : NumberInt(2), 
    "__v" : NumberInt(0), 
    "endtime" : ISODate("2016-12-29T09:26:54.360+0000"), 
    "updatedcyclenums" : NumberInt(1)
}
{ 
    "_id" : ObjectId("586499cf73d5bd3aff085a3d"), 
    "RecordID" : NumberInt(26), 
    "stationid" : ObjectId("58492195d51ad2238a1af6b1"), 
    "starttime" : ISODate("2016-12-29T05:09:17.331+0000"), 
    "cyclenums" : NumberInt(0), 
    "updateStatus" : NumberInt(1), 
    "stationtype" : "Minor", 
    "offpeekduration" : 1.2609083333333333, 
    "peekduration" : 1.2609083333333333, 
    "timeduration" : 2.5218166666666666, 
    "status" : NumberInt(2), 
    "__v" : NumberInt(0), 
    "endtime" : ISODate("2016-12-29T05:11:48.640+0000"), 
    "updatedcyclenums" : NumberInt(1)
}
{ 
    "_id" : ObjectId("58649a6d20a79e3c19100ed9"), 
    "RecordID" : NumberInt(27), 
    "stationid" : ObjectId("58492195d51ad2238a1af6b1"), 
    "starttime" : ISODate("2016-12-29T05:11:56.216+0000"), 
    "cyclenums" : NumberInt(0), 
    "updateStatus" : NumberInt(1), 
    "stationtype" : "Minor", 
    "offpeekduration" : 0.48688333333333333, 
    "peekduration" : 0.48688333333333333, 
    "timeduration" : 0.9737666666666667, 
    "status" : NumberInt(2), 
    "__v" : NumberInt(0), 
    "endtime" : ISODate("2016-12-29T05:12:54.642+0000"), 
    "updatedcyclenums" : NumberInt(1)
}
{ 
    "_id" : ObjectId("5864d608786e6943211b25e2"), 
    "RecordID" : NumberInt(28), 
    "stationid" : ObjectId("584922ef577e7e6f43b7734f"), 
    "starttime" : ISODate("2016-12-29T09:25:25.696+0000"), 
    "cyclenums" : NumberInt(0), 
    "updateStatus" : NumberInt(1), 
    "stationtype" : "Minor", 
    "offpeekduration" : 0.872225, 
    "peekduration" : 0.872225, 
    "timeduration" : 1.74445, 
    "status" : NumberInt(2), 
    "__v" : NumberInt(0), 
    "endtime" : ISODate("2016-12-29T09:27:10.363+0000"), 
    "updatedcyclenums" : NumberInt(1)
}
{ 
    "_id" : ObjectId("5864d621786e6943211b2608"), 
    "RecordID" : NumberInt(29), 
    "stationid" : ObjectId("584922ef577e7e6f43b7734f"), 
    "starttime" : ISODate("2016-12-29T09:25:50.783+0000"), 
    "cyclenums" : NumberInt(0), 
    "updateStatus" : NumberInt(1), 
    "stationtype" : "Minor", 
    "offpeekduration" : 0.76325, 
    "peekduration" : 0.76325, 
    "timeduration" : 1.5265, 
    "status" : NumberInt(2), 
    "__v" : NumberInt(0), 
    "endtime" : ISODate("2016-12-29T09:27:22.373+0000"), 
    "updatedcyclenums" : NumberInt(1)
}
{ 
    "_id" : ObjectId("5864d634786e6943211b2631"), 
    "RecordID" : NumberInt(30), 
    "stationid" : ObjectId("584922ef577e7e6f43b7734f"), 
    "starttime" : ISODate("2016-12-29T09:26:10.822+0000"), 
    "cyclenums" : NumberInt(0), 
    "updateStatus" : NumberInt(1), 
    "stationtype" : "Minor", 
    "offpeekduration" : 0.7131916666666667, 
    "peekduration" : 0.7131916666666667, 
    "timeduration" : 1.4263833333333333, 
    "status" : NumberInt(2), 
    "__v" : NumberInt(0), 
    "endtime" : ISODate("2016-12-29T09:27:36.405+0000"), 
    "updatedcyclenums" : NumberInt(1)
}
{ 
    "_id" : ObjectId("5864d64c786e6943211b2654"), 
    "RecordID" : NumberInt(31), 
    "stationid" : ObjectId("584922ef577e7e6f43b7734f"), 
    "starttime" : ISODate("2016-12-29T09:26:35.633+0000"), 
    "cyclenums" : NumberInt(0), 
    "updateStatus" : NumberInt(1), 
    "stationtype" : "Minor", 
    "offpeekduration" : 0.638175, 
    "peekduration" : 0.638175, 
    "timeduration" : 1.27635, 
    "status" : NumberInt(2), 
    "__v" : NumberInt(0), 
    "endtime" : ISODate("2016-12-29T09:27:52.214+0000"), 
    "updatedcyclenums" : NumberInt(1)
}
{ 
    "_id" : ObjectId("5864d664786e6943211b267d"), 
    "RecordID" : NumberInt(32), 
    "stationid" : ObjectId("584922ef577e7e6f43b7734f"), 
    "starttime" : ISODate("2016-12-29T09:26:58.093+0000"), 
    "cyclenums" : NumberInt(0), 
    "updateStatus" : NumberInt(1), 
    "stationtype" : "Minor", 
    "offpeekduration" : 0.5679916666666667, 
    "peekduration" : 0.5679916666666667, 
    "timeduration" : 1.1359833333333333, 
    "status" : NumberInt(2), 
    "__v" : NumberInt(0), 
    "endtime" : ISODate("2016-12-29T09:28:06.252+0000"), 
    "updatedcyclenums" : NumberInt(1)
}
{ 
    "_id" : ObjectId("5864d673786e6943211b26a0"), 
    "RecordID" : NumberInt(33), 
    "stationid" : ObjectId("584922ef577e7e6f43b7734f"), 
    "starttime" : ISODate("2016-12-29T09:27:14.078+0000"), 
    "cyclenums" : NumberInt(0), 
    "updateStatus" : NumberInt(1), 
    "stationtype" : "Minor", 
    "offpeekduration" : 0.5511333333333334, 
    "peekduration" : 0.5511333333333334, 
    "timeduration" : 1.1022666666666667, 
    "status" : NumberInt(2), 
    "__v" : NumberInt(0), 
    "endtime" : ISODate("2016-12-29T09:28:20.214+0000"), 
    "updatedcyclenums" : NumberInt(1)
}
{ 
    "_id" : ObjectId("5864d67f786e6943211b26c3"), 
    "RecordID" : NumberInt(34), 
    "stationid" : ObjectId("584922ef577e7e6f43b7734f"), 
    "starttime" : ISODate("2016-12-29T09:27:26.159+0000"), 
    "cyclenums" : NumberInt(0), 
    "updateStatus" : NumberInt(1), 
    "stationtype" : "Minor", 
    "offpeekduration" : 0.5672666666666667, 
    "peekduration" : 0.5672666666666667, 
    "timeduration" : 1.1345333333333334, 
    "status" : NumberInt(2), 
    "__v" : NumberInt(0), 
    "endtime" : ISODate("2016-12-29T09:28:34.231+0000"), 
    "updatedcyclenums" : NumberInt(1)
}
{ 
    "_id" : ObjectId("5864d68d786e6943211b26e9"), 
    "RecordID" : NumberInt(35), 
    "stationid" : ObjectId("584922ef577e7e6f43b7734f"), 
    "starttime" : ISODate("2016-12-29T09:27:40.222+0000"), 
    "cyclenums" : NumberInt(0), 
    "updateStatus" : NumberInt(1), 
    "stationtype" : "Minor", 
    "offpeekduration" : 0.6000833333333333, 
    "peekduration" : 0.6000833333333333, 
    "timeduration" : 1.2001666666666666, 
    "status" : NumberInt(2), 
    "__v" : NumberInt(0), 
    "endtime" : ISODate("2016-12-29T09:28:52.232+0000"), 
    "updatedcyclenums" : NumberInt(1)
}
{ 
    "_id" : ObjectId("5864d69f786e6943211b270f"), 
    "RecordID" : NumberInt(36), 
    "stationid" : ObjectId("584922ef577e7e6f43b7734f"), 
    "starttime" : ISODate("2016-12-29T09:27:57.026+0000"), 
    "cyclenums" : NumberInt(0), 
    "updateStatus" : NumberInt(1), 
    "stationtype" : "Minor", 
    "offpeekduration" : 0.5602916666666666, 
    "peekduration" : 0.5602916666666666, 
    "timeduration" : 1.1205833333333333, 
    "status" : NumberInt(2), 
    "__v" : NumberInt(0), 
    "endtime" : ISODate("2016-12-29T09:29:04.261+0000"), 
    "updatedcyclenums" : NumberInt(1)
}
{ 
    "_id" : ObjectId("5864d6ad786e6943211b2738"), 
    "RecordID" : NumberInt(37), 
    "stationid" : ObjectId("584922ef577e7e6f43b7734f"), 
    "starttime" : ISODate("2016-12-29T09:28:11.061+0000"), 
    "cyclenums" : NumberInt(0), 
    "updateStatus" : NumberInt(1), 
    "stationtype" : "Minor", 
    "offpeekduration" : 0.5433583333333334, 
    "peekduration" : 0.5433583333333334, 
    "timeduration" : 1.0867166666666668, 
    "status" : NumberInt(2), 
    "__v" : NumberInt(0), 
    "endtime" : ISODate("2016-12-29T09:29:16.264+0000"), 
    "updatedcyclenums" : NumberInt(1)
}
{ 
    "_id" : ObjectId("5864d6b9786e6943211b2761"), 
    "RecordID" : NumberInt(38), 
    "stationid" : ObjectId("584922ef577e7e6f43b7734f"), 
    "starttime" : ISODate("2016-12-29T09:28:23.777+0000"), 
    "cyclenums" : NumberInt(0), 
    "updateStatus" : NumberInt(1), 
    "stationtype" : "Minor", 
    "offpeekduration" : 0.5373583333333334, 
    "peekduration" : 0.5373583333333334, 
    "timeduration" : 1.0747166666666668, 
    "status" : NumberInt(2), 
    "__v" : NumberInt(0), 
    "endtime" : ISODate("2016-12-29T09:29:28.260+0000"), 
    "updatedcyclenums" : NumberInt(1)
}
{ 
    "_id" : ObjectId("5864d6c8786e6943211b2787"), 
    "RecordID" : NumberInt(39), 
    "stationid" : ObjectId("584922ef577e7e6f43b7734f"), 
    "starttime" : ISODate("2016-12-29T09:28:37.849+0000"), 
    "cyclenums" : NumberInt(0), 
    "updateStatus" : NumberInt(0), 
    "stationtype" : "Minor", 
    "offpeekduration" : NumberInt(0), 
    "peekduration" : NumberInt(0), 
    "timeduration" : NumberInt(0), 
    "status" : NumberInt(2), 
    "__v" : NumberInt(0)
}
{ 
    "_id" : ObjectId("5864d6da786e6943211b27b0"), 
    "RecordID" : NumberInt(40), 
    "stationid" : ObjectId("584922ef577e7e6f43b7734f"), 
    "starttime" : ISODate("2016-12-29T09:28:56.098+0000"), 
    "cyclenums" : NumberInt(0), 
    "updateStatus" : NumberInt(0), 
    "stationtype" : "Minor", 
    "offpeekduration" : NumberInt(0), 
    "peekduration" : NumberInt(0), 
    "timeduration" : NumberInt(0), 
    "status" : NumberInt(2), 
    "__v" : NumberInt(0)
}
{ 
    "_id" : ObjectId("5864d6e8786e6943211b27d9"), 
    "RecordID" : NumberInt(41), 
    "stationid" : ObjectId("584922ef577e7e6f43b7734f"), 
    "starttime" : ISODate("2016-12-29T09:29:08.064+0000"), 
    "cyclenums" : NumberInt(0), 
    "updateStatus" : NumberInt(0), 
    "stationtype" : "Minor", 
    "offpeekduration" : NumberInt(0), 
    "peekduration" : NumberInt(0), 
    "timeduration" : NumberInt(0), 
    "status" : NumberInt(2), 
    "__v" : NumberInt(0)
}
{ 
    "_id" : ObjectId("5864d6f1786e6943211b2805"), 
    "RecordID" : NumberInt(42), 
    "stationid" : ObjectId("584922ef577e7e6f43b7734f"), 
    "starttime" : ISODate("2016-12-29T09:29:19.856+0000"), 
    "cyclenums" : NumberInt(0), 
    "updateStatus" : NumberInt(0), 
    "stationtype" : "Minor", 
    "offpeekduration" : NumberInt(0), 
    "peekduration" : NumberInt(0), 
    "timeduration" : NumberInt(0), 
    "status" : NumberInt(2), 
    "__v" : NumberInt(0)
}
{ 
    "_id" : ObjectId("5864d6fd786e6943211b282e"), 
    "RecordID" : NumberInt(43), 
    "stationid" : ObjectId("584922ef577e7e6f43b7734f"), 
    "starttime" : ISODate("2016-12-29T09:29:31.945+0000"), 
    "cyclenums" : NumberInt(0), 
    "updateStatus" : NumberInt(0), 
    "stationtype" : "Minor", 
    "offpeekduration" : NumberInt(0), 
    "peekduration" : NumberInt(0), 
    "timeduration" : NumberInt(0), 
    "status" : NumberInt(2), 
    "__v" : NumberInt(0)
}
{ 
    "_id" : ObjectId("586507126a436f3b6fd12c71"), 
    "RecordID" : NumberInt(44), 
    "stationid" : ObjectId("58492195d51ad2238a1af6b1"), 
    "starttime" : ISODate("2016-12-29T11:55:39.782+0000"), 
    "cyclenums" : NumberInt(0), 
    "updateStatus" : NumberInt(0), 
    "stationtype" : "Minor", 
    "offpeekduration" : NumberInt(0), 
    "peekduration" : NumberInt(0), 
    "timeduration" : NumberInt(0), 
    "status" : NumberInt(2), 
    "__v" : NumberInt(0)
}
{ 
    "_id" : ObjectId("586507126a436f3b6fd12c73"), 
    "RecordID" : NumberInt(45), 
    "stationid" : ObjectId("58492195d51ad2238a1af6b1"), 
    "starttime" : ISODate("2016-12-29T11:55:18.867+0000"), 
    "cyclenums" : NumberInt(0), 
    "updateStatus" : NumberInt(0), 
    "stationtype" : "Minor", 
    "offpeekduration" : NumberInt(0), 
    "peekduration" : NumberInt(0), 
    "timeduration" : NumberInt(0), 
    "status" : NumberInt(2), 
    "__v" : NumberInt(0)
}
{ 
    "_id" : ObjectId("586507126a436f3b6fd12c74"), 
    "RecordID" : NumberInt(46), 
    "stationid" : ObjectId("58492195d51ad2238a1af6b1"), 
    "starttime" : ISODate("2016-12-29T11:55:10.914+0000"), 
    "cyclenums" : NumberInt(0), 
    "updateStatus" : NumberInt(0), 
    "stationtype" : "Minor", 
    "offpeekduration" : NumberInt(0), 
    "peekduration" : NumberInt(0), 
    "timeduration" : NumberInt(0), 
    "status" : NumberInt(2), 
    "__v" : NumberInt(0)
}
{ 
    "_id" : ObjectId("586507126a436f3b6fd12c72"), 
    "RecordID" : NumberInt(47), 
    "stationid" : ObjectId("58492195d51ad2238a1af6b1"), 
    "starttime" : ISODate("2016-12-29T11:55:50.898+0000"), 
    "cyclenums" : NumberInt(0), 
    "updateStatus" : NumberInt(0), 
    "stationtype" : "Minor", 
    "offpeekduration" : NumberInt(0), 
    "peekduration" : NumberInt(0), 
    "timeduration" : NumberInt(0), 
    "status" : NumberInt(2), 
    "__v" : NumberInt(0)
}
{ 
    "_id" : ObjectId("586507126a436f3b6fd12c76"), 
    "RecordID" : NumberInt(49), 
    "stationid" : ObjectId("58492195d51ad2238a1af6b1"), 
    "starttime" : ISODate("2016-12-29T11:54:16.683+0000"), 
    "cyclenums" : NumberInt(0), 
    "updateStatus" : NumberInt(0), 
    "stationtype" : "Minor", 
    "offpeekduration" : NumberInt(0), 
    "peekduration" : NumberInt(0), 
    "timeduration" : NumberInt(0), 
    "status" : NumberInt(2), 
    "__v" : NumberInt(0)
}
{ 
    "_id" : ObjectId("586507126a436f3b6fd12c75"), 
    "RecordID" : NumberInt(48), 
    "stationid" : ObjectId("58492195d51ad2238a1af6b1"), 
    "starttime" : ISODate("2016-12-29T11:54:52.287+0000"), 
    "cyclenums" : NumberInt(0), 
    "updateStatus" : NumberInt(0), 
    "stationtype" : "Minor", 
    "offpeekduration" : NumberInt(0), 
    "peekduration" : NumberInt(0), 
    "timeduration" : NumberInt(0), 
    "status" : NumberInt(2), 
    "__v" : NumberInt(0)
}
{ 
    "_id" : ObjectId("586507126a436f3b6fd12c79"), 
    "RecordID" : NumberInt(50), 
    "stationid" : ObjectId("58492195d51ad2238a1af6b1"), 
    "starttime" : ISODate("2016-12-29T11:54:29.330+0000"), 
    "cyclenums" : NumberInt(0), 
    "updateStatus" : NumberInt(0), 
    "stationtype" : "Minor", 
    "offpeekduration" : NumberInt(0), 
    "peekduration" : NumberInt(0), 
    "timeduration" : NumberInt(0), 
    "status" : NumberInt(2), 
    "__v" : NumberInt(0)
}
{ 
    "_id" : ObjectId("586507126a436f3b6fd12c7a"), 
    "RecordID" : NumberInt(51), 
    "stationid" : ObjectId("58492195d51ad2238a1af6b1"), 
    "starttime" : ISODate("2016-12-29T11:55:27.344+0000"), 
    "cyclenums" : NumberInt(0), 
    "updateStatus" : NumberInt(0), 
    "stationtype" : "Minor", 
    "offpeekduration" : NumberInt(0), 
    "peekduration" : NumberInt(0), 
    "timeduration" : NumberInt(0), 
    "status" : NumberInt(2), 
    "__v" : NumberInt(0)
}
{ 
    "_id" : ObjectId("586507126a436f3b6fd12c7b"), 
    "RecordID" : NumberInt(52), 
    "stationid" : ObjectId("58492195d51ad2238a1af6b1"), 
    "starttime" : ISODate("2016-12-29T11:54:07.731+0000"), 
    "cyclenums" : NumberInt(0), 
    "updateStatus" : NumberInt(0), 
    "stationtype" : "Minor", 
    "offpeekduration" : NumberInt(0), 
    "peekduration" : NumberInt(0), 
    "timeduration" : NumberInt(0), 
    "status" : NumberInt(2), 
    "__v" : NumberInt(0)
}
{ 
    "_id" : ObjectId("586749d26a436f3b6fd12ec7"), 
    "RecordID" : NumberInt(53), 
    "stationid" : ObjectId("58491323d51ad2238a1af65b"), 
    "starttime" : ISODate("2016-12-31T06:02:22.040+0000"), 
    "cyclenums" : NumberInt(0), 
    "updateStatus" : NumberInt(1), 
    "stationtype" : "Minor", 
    "offpeekduration" : 10.114891666666667, 
    "peekduration" : 10.114891666666667, 
    "timeduration" : 20.229783333333334, 
    "status" : NumberInt(2), 
    "__v" : NumberInt(0), 
    "endtime" : ISODate("2016-12-31T06:22:35.827+0000"), 
    "updatedcyclenums" : NumberInt(1)
}
{ 
    "_id" : ObjectId("586792886a436f3b6fd12f02"), 
    "RecordID" : NumberInt(54), 
    "stationid" : ObjectId("58491323d51ad2238a1af65b"), 
    "starttime" : ISODate("2016-12-31T11:12:39.261+0000"), 
    "cyclenums" : NumberInt(0), 
    "updateStatus" : NumberInt(1), 
    "stationtype" : "Minor", 
    "offpeekduration" : 0.128625, 
    "peekduration" : 0.128625, 
    "timeduration" : 0.25725, 
    "status" : NumberInt(2), 
    "__v" : NumberInt(0), 
    "endtime" : ISODate("2016-12-31T11:12:54.696+0000"), 
    "updatedcyclenums" : NumberInt(1)
}
